{
    "Accurate Shot": {"tests": "Bs", "max":"BSB"},
    "Acute Sense": {"tests": "Perception", "max":"IB"},
    "Aetheryic Attunement": {"tests": "Channelling (Any)", "max":"IB"},
    "Alley Cat": {"tests": "Stealth (Urban)", "max":"IB"},
    "Ambidextrous" : {"tests": null, "max":2},
    "Animal Affinity": {"tests": "Charm Animal", "max":"WPB"},
    "Arcane Magic (Lore)": {"tests": null, "max":1},
    "Argumentative": {"tests": "Charm", "max":"FelB"},
    "Artistic" : {"tests": "Trade (Artist)", "max":"DexB"},
    "Attractive": {"tests": "Charm", "max":"FelB"},
    "Battle Rage": {"tests": "Melee", "max":"WPB"},
    "Beat Blade": {"tests": "Melee", "max":"WSB"},
    "Beneath Notice": {"tests": "Stealth", "max":"FelB"},
    "Berserk Charge": {"tests": "Melee", "max":"SB"},
    "Blather": {"tests": "Charm", "max":"FelB"},
    "Bless (Divine Lore)": {"tests": null, "max": 1},
    "Bookish" : {"tests": "Research", "max": "IB"},
    "Carouser" : {"tests":["Charm","Consume Alcohol","Gossip"], "max":"TB"},
    "Coolheaded" : {"tests": null, "max":1, "stat_mod":"+5 WP"},
    "Criminal": {"tests":null, "max":Infinity},
    "Etiquette": {"tests":["Charm", "Gossip"], "max":"FelB", "group":true},
    "Field Dressing": {"tests": "Heal", "max": "IntB"},
    "Read/Write": {"tests": null, "max":1},
    "Resistance": {"tests": null, "max":"TB", "group":true},
    "Savvy": {"tests":null, "max":1, "stat_mod":"+5 Int"},
    "Strike to Injure": {"tests": null, "max":"IB"},
    "Strike to Stun": {"tests":"Melee", "max":"WSB"},
    "Super Numerate": {"tests":["Evaluate","Gamble"],"max":"IntB"},
    "Surgery": {"tests": "Heal", "max": "IntB"}
}